<annotation>
	<folder>Train</folder>
	<filename>191.jpeg</filename>
	<path>D:\Studies\Project\Dataset\Train\191.jpeg</path>
	<source>
		<database>Unknown</database>
	</source>
	<size>
		<width>768</width>
		<height>1024</height>
		<depth>3</depth>
	</size>
	<segmented>0</segmented>
	<object>
		<name>fat</name>
		<pose>Unspecified</pose>
		<truncated>0</truncated>
		<difficult>0</difficult>
		<bndbox>
			<xmin>177</xmin>
			<ymin>492</ymin>
			<xmax>371</xmax>
			<ymax>667</ymax>
		</bndbox>
	</object>
	<object>
		<name>salt</name>
		<pose>Unspecified</pose>
		<truncated>0</truncated>
		<difficult>0</difficult>
		<bndbox>
			<xmin>364</xmin>
			<ymin>501</ymin>
			<xmax>565</xmax>
			<ymax>664</ymax>
		</bndbox>
	</object>
</annotation>
