<annotation>
	<folder>Train</folder>
	<filename>194.jpeg</filename>
	<path>D:\Studies\Project\Dataset\Train\194.jpeg</path>
	<source>
		<database>Unknown</database>
	</source>
	<size>
		<width>900</width>
		<height>1600</height>
		<depth>3</depth>
	</size>
	<segmented>0</segmented>
	<object>
		<name>sugar</name>
		<pose>Unspecified</pose>
		<truncated>0</truncated>
		<difficult>0</difficult>
		<bndbox>
			<xmin>156</xmin>
			<ymin>903</ymin>
			<xmax>387</xmax>
			<ymax>1126</ymax>
		</bndbox>
	</object>
	<object>
		<name>fat</name>
		<pose>Unspecified</pose>
		<truncated>0</truncated>
		<difficult>0</difficult>
		<bndbox>
			<xmin>379</xmin>
			<ymin>910</ymin>
			<xmax>621</xmax>
			<ymax>1128</ymax>
		</bndbox>
	</object>
</annotation>
